ubk/__init__.py
ubk/client/__init__.py
ubk/client/client.py
ubk/exceptions/__init__.py
ubk/exceptions/service.py
ubk/types/__init__.py
ubk/types/http/__init__.py
ubk/types/http/rpc_error.py
ubk/types/http/rpc_request.py
ubk/types/http/rpc_response.py
ubk/utils/__init__.py
ubk/utils/decorator.py
ubk_pkg-0.9.5.dist-info/METADATA
ubk_pkg-0.9.5.dist-info/WHEEL
ubk_pkg-0.9.5.dist-info/top_level.txt
ubk_pkg-0.9.5.dist-info/RECORD
