Metadata-Version: 2.1
Name: ubk-pkg
Version: 0.9.5
Summary: UNKNOWN
Home-page: https://github.com/paytechuz/ubk-pkg
Author: paytechuz
Author-email: paytechuz@gmail.com
License: MIT
Keywords: account2card universal-bank ubk-pkg
Platform: UNKNOWN
Requires-Dist: requests (==2.*)
Requires-Dist: pydantic (==2.4.2)
Requires-Dist: dataclasses (==0.*)
